{
	"id": 0,
	"name": "@stacks/common 1.0.0-beta.7 Library Reference",
	"kind": 0,
	"flags": {},
	"children": [
		{
			"id": 5,
			"name": "ChainID",
			"kind": 4,
			"kindString": "Enumeration",
			"flags": {
				"isExported": true
			},
			"children": [
				{
					"id": 7,
					"name": "Mainnet",
					"kind": 16,
					"kindString": "Enumeration member",
					"flags": {
						"isExported": true
					},
					"sources": [
						{
							"fileName": "packages/common/src/constants.ts",
							"line": 3,
							"character": 9
						}
					],
					"defaultValue": "1"
				},
				{
					"id": 6,
					"name": "Testnet",
					"kind": 16,
					"kindString": "Enumeration member",
					"flags": {
						"isExported": true
					},
					"sources": [
						{
							"fileName": "packages/common/src/constants.ts",
							"line": 2,
							"character": 9
						}
					],
					"defaultValue": "2147483648"
				}
			],
			"groups": [
				{
					"title": "Enumeration members",
					"kind": 16,
					"children": [
						7,
						6
					]
				}
			],
			"sources": [
				{
					"fileName": "packages/common/src/constants.ts",
					"line": 1,
					"character": 12
				}
			]
		},
		{
			"id": 8,
			"name": "TransactionVersion",
			"kind": 4,
			"kindString": "Enumeration",
			"flags": {
				"isExported": true
			},
			"children": [
				{
					"id": 9,
					"name": "Mainnet",
					"kind": 16,
					"kindString": "Enumeration member",
					"flags": {
						"isExported": true
					},
					"sources": [
						{
							"fileName": "packages/common/src/constants.ts",
							"line": 7,
							"character": 9
						}
					],
					"defaultValue": "0"
				},
				{
					"id": 10,
					"name": "Testnet",
					"kind": 16,
					"kindString": "Enumeration member",
					"flags": {
						"isExported": true
					},
					"sources": [
						{
							"fileName": "packages/common/src/constants.ts",
							"line": 8,
							"character": 9
						}
					],
					"defaultValue": "128"
				}
			],
			"groups": [
				{
					"title": "Enumeration members",
					"kind": 16,
					"children": [
						9,
						10
					]
				}
			],
			"sources": [
				{
					"fileName": "packages/common/src/constants.ts",
					"line": 6,
					"character": 23
				}
			]
		},
		{
			"id": 326,
			"name": "GetGlobalObjectOptions",
			"kind": 256,
			"kindString": "Interface",
			"flags": {
				"isExported": true
			},
			"children": [
				{
					"id": 329,
					"name": "returnEmptyObject",
					"kind": 1024,
					"kindString": "Property",
					"flags": {
						"isExported": true,
						"isOptional": true
					},
					"comment": {
						"shortText": "If the object is not found, return an new empty object instead of undefined.\nRequires [[throwIfUnavailable]] to be falsey.",
						"tags": [
							{
								"tag": "default",
								"text": "false\n"
							}
						]
					},
					"sources": [
						{
							"fileName": "packages/common/src/utils.ts",
							"line": 243,
							"character": 19
						}
					],
					"type": {
						"type": "union",
						"types": [
							{
								"type": "intrinsic",
								"name": "undefined"
							},
							{
								"type": "intrinsic",
								"name": "false"
							},
							{
								"type": "intrinsic",
								"name": "true"
							}
						]
					}
				},
				{
					"id": 327,
					"name": "throwIfUnavailable",
					"kind": 1024,
					"kindString": "Property",
					"flags": {
						"isExported": true,
						"isOptional": true
					},
					"comment": {
						"shortText": "Throw an error if the object is not found.",
						"tags": [
							{
								"tag": "default",
								"text": "false\n"
							}
						]
					},
					"sources": [
						{
							"fileName": "packages/common/src/utils.ts",
							"line": 233,
							"character": 20
						}
					],
					"type": {
						"type": "union",
						"types": [
							{
								"type": "intrinsic",
								"name": "undefined"
							},
							{
								"type": "intrinsic",
								"name": "false"
							},
							{
								"type": "intrinsic",
								"name": "true"
							}
						]
					}
				},
				{
					"id": 328,
					"name": "usageDesc",
					"kind": 1024,
					"kindString": "Property",
					"flags": {
						"isExported": true,
						"isOptional": true
					},
					"comment": {
						"shortText": "Additional information to include in an error if thrown."
					},
					"sources": [
						{
							"fileName": "packages/common/src/utils.ts",
							"line": 237,
							"character": 11
						}
					],
					"type": {
						"type": "union",
						"types": [
							{
								"type": "intrinsic",
								"name": "undefined"
							},
							{
								"type": "intrinsic",
								"name": "string"
							}
						]
					}
				}
			],
			"groups": [
				{
					"title": "Properties",
					"kind": 1024,
					"children": [
						329,
						327,
						328
					]
				}
			],
			"sources": [
				{
					"fileName": "packages/common/src/utils.ts",
					"line": 228,
					"character": 32
				}
			]
		},
		{
			"id": 157,
			"name": "HubErrorDetails",
			"kind": 256,
			"kindString": "Interface",
			"flags": {
				"isExported": true
			},
			"indexSignature": [
				{
					"id": 161,
					"name": "__index",
					"kind": 8192,
					"kindString": "Index signature",
					"flags": {
						"isExported": true
					},
					"parameters": [
						{
							"id": 162,
							"name": "prop",
							"kind": 32768,
							"kindString": "Parameter",
							"flags": {
								"isExported": true
							},
							"type": {
								"type": "intrinsic",
								"name": "string"
							}
						}
					],
					"type": {
						"type": "intrinsic",
						"name": "any"
					}
				}
			],
			"children": [
				{
					"id": 158,
					"name": "message",
					"kind": 1024,
					"kindString": "Property",
					"flags": {
						"isExported": true,
						"isOptional": true
					},
					"sources": [
						{
							"fileName": "packages/common/src/errors.ts",
							"line": 217,
							"character": 9
						}
					],
					"type": {
						"type": "union",
						"types": [
							{
								"type": "intrinsic",
								"name": "undefined"
							},
							{
								"type": "intrinsic",
								"name": "string"
							}
						]
					}
				},
				{
					"id": 159,
					"name": "statusCode",
					"kind": 1024,
					"kindString": "Property",
					"flags": {
						"isExported": true
					},
					"sources": [
						{
							"fileName": "packages/common/src/errors.ts",
							"line": 218,
							"character": 12
						}
					],
					"type": {
						"type": "intrinsic",
						"name": "number"
					}
				},
				{
					"id": 160,
					"name": "statusText",
					"kind": 1024,
					"kindString": "Property",
					"flags": {
						"isExported": true
					},
					"sources": [
						{
							"fileName": "packages/common/src/errors.ts",
							"line": 219,
							"character": 12
						}
					],
					"type": {
						"type": "intrinsic",
						"name": "string"
					}
				}
			],
			"groups": [
				{
					"title": "Properties",
					"kind": 1024,
					"children": [
						158,
						159,
						160
					]
				}
			],
			"sources": [
				{
					"fileName": "packages/common/src/errors.ts",
					"line": 216,
					"character": 32
				}
			]
		},
		{
			"id": 322,
			"name": "intToLevel",
			"kind": 32,
			"kindString": "Variable",
			"flags": {
				"isExported": true,
				"isConst": true
			},
			"sources": [
				{
					"fileName": "packages/common/src/logger.ts",
					"line": 6,
					"character": 16
				}
			],
			"type": {
				"type": "reflection",
				"declaration": {
					"id": 323,
					"name": "__type",
					"kind": 65536,
					"kindString": "Type literal",
					"flags": {
						"isExported": true
					},
					"indexSignature": [
						{
							"id": 324,
							"name": "__index",
							"kind": 8192,
							"kindString": "Index signature",
							"flags": {
								"isExported": true
							},
							"parameters": [
								{
									"id": 325,
									"name": "int",
									"kind": 32768,
									"kindString": "Parameter",
									"flags": {
										"isExported": true
									},
									"type": {
										"type": "intrinsic",
										"name": "number"
									}
								}
							],
							"type": {
								"type": "intrinsic",
								"name": "string"
							}
						}
					],
					"sources": [
						{
							"fileName": "packages/common/src/logger.ts",
							"line": 6,
							"character": 17
						}
					]
				}
			}
		},
		{
			"id": 318,
			"name": "levelToInt",
			"kind": 32,
			"kindString": "Variable",
			"flags": {
				"isExported": true,
				"isConst": true
			},
			"sources": [
				{
					"fileName": "packages/common/src/logger.ts",
					"line": 5,
					"character": 16
				}
			],
			"type": {
				"type": "reflection",
				"declaration": {
					"id": 319,
					"name": "__type",
					"kind": 65536,
					"kindString": "Type literal",
					"flags": {
						"isExported": true
					},
					"indexSignature": [
						{
							"id": 320,
							"name": "__index",
							"kind": 8192,
							"kindString": "Index signature",
							"flags": {
								"isExported": true
							},
							"parameters": [
								{
									"id": 321,
									"name": "level",
									"kind": 32768,
									"kindString": "Parameter",
									"flags": {
										"isExported": true
									},
									"type": {
										"type": "intrinsic",
										"name": "string"
									}
								}
							],
							"type": {
								"type": "intrinsic",
								"name": "number"
							}
						}
					],
					"sources": [
						{
							"fileName": "packages/common/src/logger.ts",
							"line": 5,
							"character": 17
						}
					]
				}
			}
		},
		{
			"id": 317,
			"name": "levels",
			"kind": 32,
			"kindString": "Variable",
			"flags": {
				"isExported": true,
				"isConst": true
			},
			"sources": [
				{
					"fileName": "packages/common/src/logger.ts",
					"line": 3,
					"character": 12
				}
			],
			"type": {
				"type": "array",
				"elementType": {
					"type": "intrinsic",
					"name": "string"
				}
			},
			"defaultValue": "['debug', 'info', 'warn', 'error', 'none']"
		},
		{
			"id": 363,
			"name": "getAPIUsageErrorMessage",
			"kind": 64,
			"kindString": "Function",
			"flags": {
				"isExported": true
			},
			"signatures": [
				{
					"id": 364,
					"name": "getAPIUsageErrorMessage",
					"kind": 4096,
					"kindString": "Call signature",
					"flags": {
						"isExported": true
					},
					"parameters": [
						{
							"id": 365,
							"name": "scopeObject",
							"kind": 32768,
							"kindString": "Parameter",
							"flags": {
								"isExported": true
							},
							"type": {
								"type": "intrinsic",
								"name": "unknown"
							}
						},
						{
							"id": 366,
							"name": "apiName",
							"kind": 32768,
							"kindString": "Parameter",
							"flags": {
								"isExported": true
							},
							"type": {
								"type": "intrinsic",
								"name": "string"
							}
						},
						{
							"id": 367,
							"name": "usageDesc",
							"kind": 32768,
							"kindString": "Parameter",
							"flags": {
								"isExported": true,
								"isOptional": true
							},
							"type": {
								"type": "union",
								"types": [
									{
										"type": "intrinsic",
										"name": "undefined"
									},
									{
										"type": "intrinsic",
										"name": "string"
									}
								]
							}
						}
					],
					"type": {
						"type": "intrinsic",
						"name": "string"
					}
				}
			],
			"sources": [
				{
					"fileName": "packages/common/src/utils.ts",
					"line": 216,
					"character": 32
				}
			]
		},
		{
			"id": 343,
			"name": "getBase64OutputLength",
			"kind": 64,
			"kindString": "Function",
			"flags": {
				"isExported": true
			},
			"signatures": [
				{
					"id": 344,
					"name": "getBase64OutputLength",
					"kind": 4096,
					"kindString": "Call signature",
					"flags": {
						"isExported": true
					},
					"comment": {
						"shortText": "Calculate the base64 encoded string length for a given input length.\nThis is equivalent to the byte length when the string is ASCII or UTF8-8\nencoded."
					},
					"parameters": [
						{
							"id": 345,
							"name": "inputByteLength",
							"kind": 32768,
							"kindString": "Parameter",
							"flags": {
								"isExported": true
							},
							"type": {
								"type": "intrinsic",
								"name": "number"
							}
						}
					],
					"type": {
						"type": "intrinsic",
						"name": "number"
					}
				}
			],
			"sources": [
				{
					"fileName": "packages/common/src/utils.ts",
					"line": 63,
					"character": 37
				}
			]
		}
	],
	"groups": [
		{
			"title": "Enumerations",
			"kind": 4,
			"children": [
				5,
				8
			]
		},
		{
			"title": "Interfaces",
			"kind": 256,
			"children": [
				326,
				157
			]
		},
		{
			"title": "Variables",
			"kind": 32,
			"children": [
				322,
				318,
				317
			]
		},
		{
			"title": "Functions",
			"kind": 64,
			"children": [
				363,
				343
			]
		}
	]
}