{
	"id": 0,
	"name": "Stacks.js 1.0.0-beta.13 Library Reference",
	"kind": 0,
	"kindString": "Project",
	"flags": {},
	"children": [
		{
			"id": 41,
			"name": "BnsContractAddress",
			"kind": 4,
			"kindString": "Enumeration",
			"flags": {
				"isConst": true
			},
			"children": [
				{
					"id": 42,
					"name": "mainnet",
					"kind": 16,
					"kindString": "Enumeration member",
					"flags": {},
					"sources": [
						{
							"fileName": "index.ts",
							"line": 30,
							"character": 9
						}
					],
					"defaultValue": "\"SP000000000000000000002Q6VF78\""
				},
				{
					"id": 43,
					"name": "testnet",
					"kind": 16,
					"kindString": "Enumeration member",
					"flags": {},
					"sources": [
						{
							"fileName": "index.ts",
							"line": 31,
							"character": 9
						}
					],
					"defaultValue": "\"ST000000000000000000002AMW42H\""
				}
			],
			"groups": [
				{
					"title": "Enumeration members",
					"kind": 16,
					"children": [
						42,
						43
					]
				}
			],
			"sources": [
				{
					"fileName": "index.ts",
					"line": 29,
					"character": 36
				}
			]
		},
		{
			"id": 65,
			"name": "BnsContractCallOptions",
			"kind": 256,
			"kindString": "Interface",
			"flags": {},
			"children": [
				{
					"id": 70,
					"name": "attachment",
					"kind": 1024,
					"kindString": "Property",
					"flags": {
						"isOptional": true
					},
					"sources": [
						{
							"fileName": "index.ts",
							"line": 68,
							"character": 12
						}
					],
					"type": {
						"type": "reference",
						"name": "Buffer"
					}
				},
				{
					"id": 67,
					"name": "functionArgs",
					"kind": 1024,
					"kindString": "Property",
					"flags": {},
					"sources": [
						{
							"fileName": "index.ts",
							"line": 65,
							"character": 14
						}
					],
					"type": {
						"type": "array",
						"elementType": {
							"type": "reference",
							"name": "ClarityValue"
						}
					}
				},
				{
					"id": 66,
					"name": "functionName",
					"kind": 1024,
					"kindString": "Property",
					"flags": {},
					"sources": [
						{
							"fileName": "index.ts",
							"line": 64,
							"character": 14
						}
					],
					"type": {
						"type": "intrinsic",
						"name": "string"
					}
				},
				{
					"id": 69,
					"name": "network",
					"kind": 1024,
					"kindString": "Property",
					"flags": {},
					"sources": [
						{
							"fileName": "index.ts",
							"line": 67,
							"character": 9
						}
					],
					"type": {
						"type": "reference",
						"name": "StacksNetwork"
					}
				},
				{
					"id": 68,
					"name": "publicKey",
					"kind": 1024,
					"kindString": "Property",
					"flags": {},
					"sources": [
						{
							"fileName": "index.ts",
							"line": 66,
							"character": 11
						}
					],
					"type": {
						"type": "intrinsic",
						"name": "string"
					}
				}
			],
			"groups": [
				{
					"title": "Properties",
					"kind": 1024,
					"children": [
						70,
						67,
						66,
						69,
						68
					]
				}
			],
			"sources": [
				{
					"fileName": "index.ts",
					"line": 63,
					"character": 39
				}
			]
		},
		{
			"id": 71,
			"name": "BnsReadOnlyOptions",
			"kind": 256,
			"kindString": "Interface",
			"flags": {},
			"children": [
				{
					"id": 73,
					"name": "functionArgs",
					"kind": 1024,
					"kindString": "Property",
					"flags": {},
					"sources": [
						{
							"fileName": "index.ts",
							"line": 87,
							"character": 14
						}
					],
					"type": {
						"type": "array",
						"elementType": {
							"type": "reference",
							"name": "ClarityValue"
						}
					}
				},
				{
					"id": 72,
					"name": "functionName",
					"kind": 1024,
					"kindString": "Property",
					"flags": {},
					"sources": [
						{
							"fileName": "index.ts",
							"line": 86,
							"character": 14
						}
					],
					"type": {
						"type": "intrinsic",
						"name": "string"
					}
				},
				{
					"id": 75,
					"name": "network",
					"kind": 1024,
					"kindString": "Property",
					"flags": {},
					"sources": [
						{
							"fileName": "index.ts",
							"line": 89,
							"character": 9
						}
					],
					"type": {
						"type": "reference",
						"name": "StacksNetwork"
					}
				},
				{
					"id": 74,
					"name": "senderAddress",
					"kind": 1024,
					"kindString": "Property",
					"flags": {},
					"sources": [
						{
							"fileName": "index.ts",
							"line": 88,
							"character": 15
						}
					],
					"type": {
						"type": "intrinsic",
						"name": "string"
					}
				}
			],
			"groups": [
				{
					"title": "Properties",
					"kind": 1024,
					"children": [
						73,
						72,
						75,
						74
					]
				}
			],
			"sources": [
				{
					"fileName": "index.ts",
					"line": 85,
					"character": 35
				}
			]
		},
		{
			"id": 76,
			"name": "CanRegisterNameOptions",
			"kind": 256,
			"kindString": "Interface",
			"flags": {},
			"comment": {
				"shortText": "Can register name options",
				"tags": [
					{
						"tag": "param",
						"text": "the fully qualified name (\"name.namespace\") to check",
						"param": "fullyQualifiedName"
					},
					{
						"tag": "param",
						"text": "the Stacks blockchain network to use\n",
						"param": "network"
					}
				]
			},
			"children": [
				{
					"id": 77,
					"name": "fullyQualifiedName",
					"kind": 1024,
					"kindString": "Property",
					"flags": {},
					"sources": [
						{
							"fileName": "index.ts",
							"line": 110,
							"character": 20
						}
					],
					"type": {
						"type": "intrinsic",
						"name": "string"
					}
				},
				{
					"id": 78,
					"name": "network",
					"kind": 1024,
					"kindString": "Property",
					"flags": {},
					"sources": [
						{
							"fileName": "index.ts",
							"line": 111,
							"character": 9
						}
					],
					"type": {
						"type": "reference",
						"name": "StacksNetwork"
					}
				}
			],
			"groups": [
				{
					"title": "Properties",
					"kind": 1024,
					"children": [
						77,
						78
					]
				}
			],
			"sources": [
				{
					"fileName": "index.ts",
					"line": 109,
					"character": 39
				}
			]
		},
		{
			"id": 82,
			"name": "GetNamePriceOptions",
			"kind": 256,
			"kindString": "Interface",
			"flags": {},
			"comment": {
				"shortText": "Get name price options",
				"tags": [
					{
						"tag": "param",
						"text": "the fully qualified name (\"name.namespace\") to get the price of",
						"param": "fullyQualifiedName"
					},
					{
						"tag": "param",
						"text": "the Stacks blockchain network to use\n",
						"param": "network"
					}
				]
			},
			"children": [
				{
					"id": 83,
					"name": "fullyQualifiedName",
					"kind": 1024,
					"kindString": "Property",
					"flags": {},
					"sources": [
						{
							"fileName": "index.ts",
							"line": 210,
							"character": 20
						}
					],
					"type": {
						"type": "intrinsic",
						"name": "string"
					}
				},
				{
					"id": 84,
					"name": "network",
					"kind": 1024,
					"kindString": "Property",
					"flags": {},
					"sources": [
						{
							"fileName": "index.ts",
							"line": 211,
							"character": 9
						}
					],
					"type": {
						"type": "reference",
						"name": "StacksNetwork"
					}
				}
			],
			"groups": [
				{
					"title": "Properties",
					"kind": 1024,
					"children": [
						83,
						84
					]
				}
			],
			"sources": [
				{
					"fileName": "index.ts",
					"line": 209,
					"character": 36
				}
			]
		},
		{
			"id": 79,
			"name": "GetNamespacePriceOptions",
			"kind": 256,
			"kindString": "Interface",
			"flags": {},
			"comment": {
				"shortText": "Get namespace price options",
				"tags": [
					{
						"tag": "param",
						"text": "the namespace to get the price of",
						"param": "namespace"
					},
					{
						"tag": "param",
						"text": "the Stacks blockchain network to use\n",
						"param": "network"
					}
				]
			},
			"children": [
				{
					"id": 80,
					"name": "namespace",
					"kind": 1024,
					"kindString": "Property",
					"flags": {},
					"sources": [
						{
							"fileName": "index.ts",
							"line": 159,
							"character": 11
						}
					],
					"type": {
						"type": "intrinsic",
						"name": "string"
					}
				},
				{
					"id": 81,
					"name": "network",
					"kind": 1024,
					"kindString": "Property",
					"flags": {},
					"sources": [
						{
							"fileName": "index.ts",
							"line": 160,
							"character": 9
						}
					],
					"type": {
						"type": "reference",
						"name": "StacksNetwork"
					}
				}
			],
			"groups": [
				{
					"title": "Properties",
					"kind": 1024,
					"children": [
						80,
						81
					]
				}
			],
			"sources": [
				{
					"fileName": "index.ts",
					"line": 158,
					"character": 41
				}
			]
		},
		{
			"id": 99,
			"name": "ImportNameOptions",
			"kind": 256,
			"kindString": "Interface",
			"flags": {},
			"comment": {
				"shortText": "Namespace name import options",
				"tags": [
					{
						"tag": "param",
						"text": "the namespace to import name into",
						"param": "namespace"
					},
					{
						"tag": "param",
						"text": "the name to import",
						"param": "name"
					},
					{
						"tag": "param",
						"text": "the address to register the name to",
						"param": "beneficiary"
					},
					{
						"tag": "param",
						"text": "the zonefile hash to register",
						"param": "zonefileHash"
					},
					{
						"tag": "param",
						"text": "the private key to sign the transaction",
						"param": "publicKey"
					},
					{
						"tag": "param",
						"text": "the Stacks blockchain network to use\n",
						"param": "network"
					}
				]
			},
			"children": [
				{
					"id": 102,
					"name": "beneficiary",
					"kind": 1024,
					"kindString": "Property",
					"flags": {},
					"sources": [
						{
							"fileName": "index.ts",
							"line": 392,
							"character": 13
						}
					],
					"type": {
						"type": "intrinsic",
						"name": "string"
					}
				},
				{
					"id": 101,
					"name": "name",
					"kind": 1024,
					"kindString": "Property",
					"flags": {},
					"sources": [
						{
							"fileName": "index.ts",
							"line": 391,
							"character": 6
						}
					],
					"type": {
						"type": "intrinsic",
						"name": "string"
					}
				},
				{
					"id": 100,
					"name": "namespace",
					"kind": 1024,
					"kindString": "Property",
					"flags": {},
					"sources": [
						{
							"fileName": "index.ts",
							"line": 390,
							"character": 11
						}
					],
					"type": {
						"type": "intrinsic",
						"name": "string"
					}
				},
				{
					"id": 105,
					"name": "network",
					"kind": 1024,
					"kindString": "Property",
					"flags": {},
					"sources": [
						{
							"fileName": "index.ts",
							"line": 395,
							"character": 9
						}
					],
					"type": {
						"type": "reference",
						"name": "StacksNetwork"
					}
				},
				{
					"id": 104,
					"name": "publicKey",
					"kind": 1024,
					"kindString": "Property",
					"flags": {},
					"sources": [
						{
							"fileName": "index.ts",
							"line": 394,
							"character": 11
						}
					],
					"type": {
						"type": "intrinsic",
						"name": "string"
					}
				},
				{
					"id": 103,
					"name": "zonefile",
					"kind": 1024,
					"kindString": "Property",
					"flags": {},
					"sources": [
						{
							"fileName": "index.ts",
							"line": 393,
							"character": 10
						}
					],
					"type": {
						"type": "intrinsic",
						"name": "string"
					}
				}
			],
			"groups": [
				{
					"title": "Properties",
					"kind": 1024,
					"children": [
						102,
						101,
						100,
						105,
						104,
						103
					]
				}
			],
			"sources": [
				{
					"fileName": "index.ts",
					"line": 389,
					"character": 34
				}
			]
		},
		{
			"id": 110,
			"name": "PreorderNameOptions",
			"kind": 256,
			"kindString": "Interface",
			"flags": {},
			"comment": {
				"shortText": "Preorder name options",
				"tags": [
					{
						"tag": "param",
						"text": "the fully qualified name to preorder including the\n                                       namespace (myName.id)",
						"param": "fullyQualifiedName"
					},
					{
						"tag": "param",
						"text": "salt used to generate the preorder name hash",
						"param": "salt"
					},
					{
						"tag": "param",
						"text": "amount of STX to burn for the registration",
						"param": "stxToBurn"
					},
					{
						"tag": "param",
						"text": "the private key to sign the transaction",
						"param": "publicKey"
					},
					{
						"tag": "param",
						"text": "the Stacks blockchain network to use\n",
						"param": "network"
					}
				]
			},
			"children": [
				{
					"id": 111,
					"name": "fullyQualifiedName",
					"kind": 1024,
					"kindString": "Property",
					"flags": {},
					"sources": [
						{
							"fileName": "index.ts",
							"line": 483,
							"character": 20
						}
					],
					"type": {
						"type": "intrinsic",
						"name": "string"
					}
				},
				{
					"id": 115,
					"name": "network",
					"kind": 1024,
					"kindString": "Property",
					"flags": {},
					"sources": [
						{
							"fileName": "index.ts",
							"line": 487,
							"character": 9
						}
					],
					"type": {
						"type": "reference",
						"name": "StacksNetwork"
					}
				},
				{
					"id": 114,
					"name": "publicKey",
					"kind": 1024,
					"kindString": "Property",
					"flags": {},
					"sources": [
						{
							"fileName": "index.ts",
							"line": 486,
							"character": 11
						}
					],
					"type": {
						"type": "intrinsic",
						"name": "string"
					}
				},
				{
					"id": 112,
					"name": "salt",
					"kind": 1024,
					"kindString": "Property",
					"flags": {},
					"sources": [
						{
							"fileName": "index.ts",
							"line": 484,
							"character": 6
						}
					],
					"type": {
						"type": "intrinsic",
						"name": "string"
					}
				},
				{
					"id": 113,
					"name": "stxToBurn",
					"kind": 1024,
					"kindString": "Property",
					"flags": {},
					"sources": [
						{
							"fileName": "index.ts",
							"line": 485,
							"character": 11
						}
					],
					"type": {
						"type": "reference",
						"name": "BN"
					}
				}
			],
			"groups": [
				{
					"title": "Properties",
					"kind": 1024,
					"children": [
						111,
						115,
						114,
						112,
						113
					]
				}
			],
			"sources": [
				{
					"fileName": "index.ts",
					"line": 482,
					"character": 36
				}
			]
		},
		{
			"id": 85,
			"name": "PreorderNamespaceOptions",
			"kind": 256,
			"kindString": "Interface",
			"flags": {},
			"comment": {
				"shortText": "Preorder namespace options",
				"tags": [
					{
						"tag": "param",
						"text": "the namespace to preorder",
						"param": "namespace"
					},
					{
						"tag": "param",
						"text": "salt used to generate the preorder namespace hash",
						"param": "salt"
					},
					{
						"tag": "param",
						"text": "amount of STX to burn for the registration",
						"param": "stxToBurn"
					},
					{
						"tag": "param",
						"text": "the private key to sign the transaction",
						"param": "publicKey"
					},
					{
						"tag": "param",
						"text": "the Stacks blockchain network to use\n",
						"param": "network"
					}
				]
			},
			"children": [
				{
					"id": 86,
					"name": "namespace",
					"kind": 1024,
					"kindString": "Property",
					"flags": {},
					"sources": [
						{
							"fileName": "index.ts",
							"line": 267,
							"character": 11
						}
					],
					"type": {
						"type": "intrinsic",
						"name": "string"
					}
				},
				{
					"id": 90,
					"name": "network",
					"kind": 1024,
					"kindString": "Property",
					"flags": {},
					"sources": [
						{
							"fileName": "index.ts",
							"line": 271,
							"character": 9
						}
					],
					"type": {
						"type": "reference",
						"name": "StacksNetwork"
					}
				},
				{
					"id": 89,
					"name": "publicKey",
					"kind": 1024,
					"kindString": "Property",
					"flags": {},
					"sources": [
						{
							"fileName": "index.ts",
							"line": 270,
							"character": 11
						}
					],
					"type": {
						"type": "intrinsic",
						"name": "string"
					}
				},
				{
					"id": 87,
					"name": "salt",
					"kind": 1024,
					"kindString": "Property",
					"flags": {},
					"sources": [
						{
							"fileName": "index.ts",
							"line": 268,
							"character": 6
						}
					],
					"type": {
						"type": "intrinsic",
						"name": "string"
					}
				},
				{
					"id": 88,
					"name": "stxToBurn",
					"kind": 1024,
					"kindString": "Property",
					"flags": {},
					"sources": [
						{
							"fileName": "index.ts",
							"line": 269,
							"character": 11
						}
					],
					"type": {
						"type": "reference",
						"name": "BN"
					}
				}
			],
			"groups": [
				{
					"title": "Properties",
					"kind": 1024,
					"children": [
						86,
						90,
						89,
						87,
						88
					]
				}
			],
			"sources": [
				{
					"fileName": "index.ts",
					"line": 266,
					"character": 41
				}
			]
		},
		{
			"id": 44,
			"name": "PriceFunction",
			"kind": 256,
			"kindString": "Interface",
			"flags": {},
			"children": [
				{
					"id": 47,
					"name": "b1",
					"kind": 1024,
					"kindString": "Property",
					"flags": {},
					"sources": [
						{
							"fileName": "index.ts",
							"line": 43,
							"character": 4
						}
					],
					"type": {
						"type": "reference",
						"name": "BN"
					}
				},
				{
					"id": 56,
					"name": "b10",
					"kind": 1024,
					"kindString": "Property",
					"flags": {},
					"sources": [
						{
							"fileName": "index.ts",
							"line": 52,
							"character": 5
						}
					],
					"type": {
						"type": "reference",
						"name": "BN"
					}
				},
				{
					"id": 57,
					"name": "b11",
					"kind": 1024,
					"kindString": "Property",
					"flags": {},
					"sources": [
						{
							"fileName": "index.ts",
							"line": 53,
							"character": 5
						}
					],
					"type": {
						"type": "reference",
						"name": "BN"
					}
				},
				{
					"id": 58,
					"name": "b12",
					"kind": 1024,
					"kindString": "Property",
					"flags": {},
					"sources": [
						{
							"fileName": "index.ts",
							"line": 54,
							"character": 5
						}
					],
					"type": {
						"type": "reference",
						"name": "BN"
					}
				},
				{
					"id": 59,
					"name": "b13",
					"kind": 1024,
					"kindString": "Property",
					"flags": {},
					"sources": [
						{
							"fileName": "index.ts",
							"line": 55,
							"character": 5
						}
					],
					"type": {
						"type": "reference",
						"name": "BN"
					}
				},
				{
					"id": 60,
					"name": "b14",
					"kind": 1024,
					"kindString": "Property",
					"flags": {},
					"sources": [
						{
							"fileName": "index.ts",
							"line": 56,
							"character": 5
						}
					],
					"type": {
						"type": "reference",
						"name": "BN"
					}
				},
				{
					"id": 61,
					"name": "b15",
					"kind": 1024,
					"kindString": "Property",
					"flags": {},
					"sources": [
						{
							"fileName": "index.ts",
							"line": 57,
							"character": 5
						}
					],
					"type": {
						"type": "reference",
						"name": "BN"
					}
				},
				{
					"id": 62,
					"name": "b16",
					"kind": 1024,
					"kindString": "Property",
					"flags": {},
					"sources": [
						{
							"fileName": "index.ts",
							"line": 58,
							"character": 5
						}
					],
					"type": {
						"type": "reference",
						"name": "BN"
					}
				},
				{
					"id": 48,
					"name": "b2",
					"kind": 1024,
					"kindString": "Property",
					"flags": {},
					"sources": [
						{
							"fileName": "index.ts",
							"line": 44,
							"character": 4
						}
					],
					"type": {
						"type": "reference",
						"name": "BN"
					}
				},
				{
					"id": 49,
					"name": "b3",
					"kind": 1024,
					"kindString": "Property",
					"flags": {},
					"sources": [
						{
							"fileName": "index.ts",
							"line": 45,
							"character": 4
						}
					],
					"type": {
						"type": "reference",
						"name": "BN"
					}
				},
				{
					"id": 50,
					"name": "b4",
					"kind": 1024,
					"kindString": "Property",
					"flags": {},
					"sources": [
						{
							"fileName": "index.ts",
							"line": 46,
							"character": 4
						}
					],
					"type": {
						"type": "reference",
						"name": "BN"
					}
				},
				{
					"id": 51,
					"name": "b5",
					"kind": 1024,
					"kindString": "Property",
					"flags": {},
					"sources": [
						{
							"fileName": "index.ts",
							"line": 47,
							"character": 4
						}
					],
					"type": {
						"type": "reference",
						"name": "BN"
					}
				},
				{
					"id": 52,
					"name": "b6",
					"kind": 1024,
					"kindString": "Property",
					"flags": {},
					"sources": [
						{
							"fileName": "index.ts",
							"line": 48,
							"character": 4
						}
					],
					"type": {
						"type": "reference",
						"name": "BN"
					}
				},
				{
					"id": 53,
					"name": "b7",
					"kind": 1024,
					"kindString": "Property",
					"flags": {},
					"sources": [
						{
							"fileName": "index.ts",
							"line": 49,
							"character": 4
						}
					],
					"type": {
						"type": "reference",
						"name": "BN"
					}
				},
				{
					"id": 54,
					"name": "b8",
					"kind": 1024,
					"kindString": "Property",
					"flags": {},
					"sources": [
						{
							"fileName": "index.ts",
							"line": 50,
							"character": 4
						}
					],
					"type": {
						"type": "reference",
						"name": "BN"
					}
				},
				{
					"id": 55,
					"name": "b9",
					"kind": 1024,
					"kindString": "Property",
					"flags": {},
					"sources": [
						{
							"fileName": "index.ts",
							"line": 51,
							"character": 4
						}
					],
					"type": {
						"type": "reference",
						"name": "BN"
					}
				},
				{
					"id": 45,
					"name": "base",
					"kind": 1024,
					"kindString": "Property",
					"flags": {},
					"sources": [
						{
							"fileName": "index.ts",
							"line": 41,
							"character": 6
						}
					],
					"type": {
						"type": "reference",
						"name": "BN"
					}
				},
				{
					"id": 46,
					"name": "coefficient",
					"kind": 1024,
					"kindString": "Property",
					"flags": {},
					"sources": [
						{
							"fileName": "index.ts",
							"line": 42,
							"character": 13
						}
					],
					"type": {
						"type": "reference",
						"name": "BN"
					}
				},
				{
					"id": 64,
					"name": "noVowelDiscount",
					"kind": 1024,
					"kindString": "Property",
					"flags": {},
					"sources": [
						{
							"fileName": "index.ts",
							"line": 60,
							"character": 17
						}
					],
					"type": {
						"type": "reference",
						"name": "BN"
					}
				},
				{
					"id": 63,
					"name": "nonAlphaDiscount",
					"kind": 1024,
					"kindString": "Property",
					"flags": {},
					"sources": [
						{
							"fileName": "index.ts",
							"line": 59,
							"character": 18
						}
					],
					"type": {
						"type": "reference",
						"name": "BN"
					}
				}
			],
			"groups": [
				{
					"title": "Properties",
					"kind": 1024,
					"children": [
						47,
						56,
						57,
						58,
						59,
						60,
						61,
						62,
						48,
						49,
						50,
						51,
						52,
						53,
						54,
						55,
						45,
						46,
						64,
						63
					]
				}
			],
			"sources": [
				{
					"fileName": "index.ts",
					"line": 40,
					"character": 30
				}
			]
		},
		{
			"id": 106,
			"name": "ReadyNamespaceOptions",
			"kind": 256,
			"kindString": "Interface",
			"flags": {},
			"comment": {
				"shortText": "Ready namespace options",
				"tags": [
					{
						"tag": "param",
						"text": "the namespace to ready",
						"param": "namespace"
					},
					{
						"tag": "param",
						"text": "the private key to sign the transaction",
						"param": "publicKey"
					},
					{
						"tag": "param",
						"text": "the Stacks blockchain network to use\n",
						"param": "network"
					}
				]
			},
			"children": [
				{
					"id": 107,
					"name": "namespace",
					"kind": 1024,
					"kindString": "Property",
					"flags": {},
					"sources": [
						{
							"fileName": "index.ts",
							"line": 441,
							"character": 11
						}
					],
					"type": {
						"type": "intrinsic",
						"name": "string"
					}
				},
				{
					"id": 109,
					"name": "network",
					"kind": 1024,
					"kindString": "Property",
					"flags": {},
					"sources": [
						{
							"fileName": "index.ts",
							"line": 443,
							"character": 9
						}
					],
					"type": {
						"type": "reference",
						"name": "StacksNetwork"
					}
				},
				{
					"id": 108,
					"name": "publicKey",
					"kind": 1024,
					"kindString": "Property",
					"flags": {},
					"sources": [
						{
							"fileName": "index.ts",
							"line": 442,
							"character": 11
						}
					],
					"type": {
						"type": "intrinsic",
						"name": "string"
					}
				}
			],
			"groups": [
				{
					"title": "Properties",
					"kind": 1024,
					"children": [
						107,
						109,
						108
					]
				}
			],
			"sources": [
				{
					"fileName": "index.ts",
					"line": 440,
					"character": 38
				}
			]
		},
		{
			"id": 116,
			"name": "RegisterNameOptions",
			"kind": 256,
			"kindString": "Interface",
			"flags": {},
			"comment": {
				"shortText": "Register name options",
				"tags": [
					{
						"tag": "param",
						"text": "the fully qualified name to preorder including the\n                                       namespace (myName.id)",
						"param": "fullyQualifiedName"
					},
					{
						"tag": "param",
						"text": "salt used to generate the preorder name hash",
						"param": "salt"
					},
					{
						"tag": "param",
						"text": "the zonefile to register with the name",
						"param": "zonefile"
					},
					{
						"tag": "param",
						"text": "the private key to sign the transaction",
						"param": "publicKey"
					},
					{
						"tag": "param",
						"text": "the Stacks blockchain network to use\n",
						"param": "network"
					}
				]
			},
			"children": [
				{
					"id": 117,
					"name": "fullyQualifiedName",
					"kind": 1024,
					"kindString": "Property",
					"flags": {},
					"sources": [
						{
							"fileName": "index.ts",
							"line": 535,
							"character": 20
						}
					],
					"type": {
						"type": "intrinsic",
						"name": "string"
					}
				},
				{
					"id": 121,
					"name": "network",
					"kind": 1024,
					"kindString": "Property",
					"flags": {},
					"sources": [
						{
							"fileName": "index.ts",
							"line": 539,
							"character": 9
						}
					],
					"type": {
						"type": "reference",
						"name": "StacksNetwork"
					}
				},
				{
					"id": 120,
					"name": "publicKey",
					"kind": 1024,
					"kindString": "Property",
					"flags": {},
					"sources": [
						{
							"fileName": "index.ts",
							"line": 538,
							"character": 11
						}
					],
					"type": {
						"type": "intrinsic",
						"name": "string"
					}
				},
				{
					"id": 118,
					"name": "salt",
					"kind": 1024,
					"kindString": "Property",
					"flags": {},
					"sources": [
						{
							"fileName": "index.ts",
							"line": 536,
							"character": 6
						}
					],
					"type": {
						"type": "intrinsic",
						"name": "string"
					}
				},
				{
					"id": 119,
					"name": "zonefile",
					"kind": 1024,
					"kindString": "Property",
					"flags": {},
					"sources": [
						{
							"fileName": "index.ts",
							"line": 537,
							"character": 10
						}
					],
					"type": {
						"type": "intrinsic",
						"name": "string"
					}
				}
			],
			"groups": [
				{
					"title": "Properties",
					"kind": 1024,
					"children": [
						117,
						121,
						120,
						118,
						119
					]
				}
			],
			"sources": [
				{
					"fileName": "index.ts",
					"line": 534,
					"character": 36
				}
			]
		},
		{
			"id": 137,
			"name": "RenewNameOptions",
			"kind": 256,
			"kindString": "Interface",
			"flags": {},
			"comment": {
				"shortText": "Renew name options",
				"tags": [
					{
						"tag": "param",
						"text": "the fully qualified name to renew including the\n                                       namespace (myName.id)",
						"param": "fullyQualifiedName"
					},
					{
						"tag": "param",
						"text": "amount of STX to burn for the registration",
						"param": "stxToBurn"
					},
					{
						"tag": "param",
						"text": "the private key to sign the transaction",
						"param": "publicKey"
					},
					{
						"tag": "param",
						"text": "optionally choose a new owner address",
						"param": "newOwnerAddress"
					},
					{
						"tag": "param",
						"text": "optionally update the zonefile hash",
						"param": "zonefileHash"
					},
					{
						"tag": "param",
						"text": "the Stacks blockchain network to use\n",
						"param": "network"
					}
				]
			},
			"children": [
				{
					"id": 138,
					"name": "fullyQualifiedName",
					"kind": 1024,
					"kindString": "Property",
					"flags": {},
					"sources": [
						{
							"fileName": "index.ts",
							"line": 748,
							"character": 20
						}
					],
					"type": {
						"type": "intrinsic",
						"name": "string"
					}
				},
				{
					"id": 141,
					"name": "network",
					"kind": 1024,
					"kindString": "Property",
					"flags": {},
					"sources": [
						{
							"fileName": "index.ts",
							"line": 751,
							"character": 9
						}
					],
					"type": {
						"type": "reference",
						"name": "StacksNetwork"
					}
				},
				{
					"id": 142,
					"name": "newOwnerAddress",
					"kind": 1024,
					"kindString": "Property",
					"flags": {
						"isOptional": true
					},
					"sources": [
						{
							"fileName": "index.ts",
							"line": 752,
							"character": 17
						}
					],
					"type": {
						"type": "intrinsic",
						"name": "string"
					}
				},
				{
					"id": 140,
					"name": "publicKey",
					"kind": 1024,
					"kindString": "Property",
					"flags": {},
					"sources": [
						{
							"fileName": "index.ts",
							"line": 750,
							"character": 11
						}
					],
					"type": {
						"type": "intrinsic",
						"name": "string"
					}
				},
				{
					"id": 139,
					"name": "stxToBurn",
					"kind": 1024,
					"kindString": "Property",
					"flags": {},
					"sources": [
						{
							"fileName": "index.ts",
							"line": 749,
							"character": 11
						}
					],
					"type": {
						"type": "reference",
						"name": "BN"
					}
				},
				{
					"id": 143,
					"name": "zonefile",
					"kind": 1024,
					"kindString": "Property",
					"flags": {
						"isOptional": true
					},
					"sources": [
						{
							"fileName": "index.ts",
							"line": 753,
							"character": 10
						}
					],
					"type": {
						"type": "intrinsic",
						"name": "string"
					}
				}
			],
			"groups": [
				{
					"title": "Properties",
					"kind": 1024,
					"children": [
						138,
						141,
						142,
						140,
						139,
						143
					]
				}
			],
			"sources": [
				{
					"fileName": "index.ts",
					"line": 747,
					"character": 33
				}
			]
		},
		{
			"id": 91,
			"name": "RevealNamespaceOptions",
			"kind": 256,
			"kindString": "Interface",
			"flags": {},
			"comment": {
				"shortText": "Reveal namespace options",
				"tags": [
					{
						"tag": "param",
						"text": "the namespace to reveal",
						"param": "namespace"
					},
					{
						"tag": "param",
						"text": "salt used to generate the preorder namespace hash",
						"param": "salt"
					},
					{
						"tag": "param",
						"text": "an object containing the price function for the namespace",
						"param": "priceFunction"
					},
					{
						"tag": "param",
						"text": "the number of blocks name registrations are valid for in the namespace",
						"param": "lifeTime"
					},
					{
						"tag": "param",
						"text": "the STX address used for name imports",
						"param": "namespaceImportAddress"
					},
					{
						"tag": "param",
						"text": "the private key to sign the transaction",
						"param": "publicKey"
					},
					{
						"tag": "param",
						"text": "the Stacks blockchain network to use\n",
						"param": "network"
					}
				]
			},
			"children": [
				{
					"id": 95,
					"name": "lifetime",
					"kind": 1024,
					"kindString": "Property",
					"flags": {},
					"sources": [
						{
							"fileName": "index.ts",
							"line": 319,
							"character": 10
						}
					],
					"type": {
						"type": "reference",
						"name": "BN"
					}
				},
				{
					"id": 92,
					"name": "namespace",
					"kind": 1024,
					"kindString": "Property",
					"flags": {},
					"sources": [
						{
							"fileName": "index.ts",
							"line": 316,
							"character": 11
						}
					],
					"type": {
						"type": "intrinsic",
						"name": "string"
					}
				},
				{
					"id": 96,
					"name": "namespaceImportAddress",
					"kind": 1024,
					"kindString": "Property",
					"flags": {},
					"sources": [
						{
							"fileName": "index.ts",
							"line": 320,
							"character": 24
						}
					],
					"type": {
						"type": "intrinsic",
						"name": "string"
					}
				},
				{
					"id": 98,
					"name": "network",
					"kind": 1024,
					"kindString": "Property",
					"flags": {},
					"sources": [
						{
							"fileName": "index.ts",
							"line": 322,
							"character": 9
						}
					],
					"type": {
						"type": "reference",
						"name": "StacksNetwork"
					}
				},
				{
					"id": 94,
					"name": "priceFunction",
					"kind": 1024,
					"kindString": "Property",
					"flags": {},
					"sources": [
						{
							"fileName": "index.ts",
							"line": 318,
							"character": 15
						}
					],
					"type": {
						"type": "reference",
						"id": 44,
						"name": "PriceFunction"
					}
				},
				{
					"id": 97,
					"name": "publicKey",
					"kind": 1024,
					"kindString": "Property",
					"flags": {},
					"sources": [
						{
							"fileName": "index.ts",
							"line": 321,
							"character": 11
						}
					],
					"type": {
						"type": "intrinsic",
						"name": "string"
					}
				},
				{
					"id": 93,
					"name": "salt",
					"kind": 1024,
					"kindString": "Property",
					"flags": {},
					"sources": [
						{
							"fileName": "index.ts",
							"line": 317,
							"character": 6
						}
					],
					"type": {
						"type": "intrinsic",
						"name": "string"
					}
				}
			],
			"groups": [
				{
					"title": "Properties",
					"kind": 1024,
					"children": [
						95,
						92,
						96,
						98,
						94,
						97,
						93
					]
				}
			],
			"sources": [
				{
					"fileName": "index.ts",
					"line": 315,
					"character": 39
				}
			]
		},
		{
			"id": 133,
			"name": "RevokeNameOptions",
			"kind": 256,
			"kindString": "Interface",
			"flags": {},
			"comment": {
				"shortText": "Revoke name options",
				"tags": [
					{
						"tag": "param",
						"text": "the fully qualified name to revoke including the\n                                       namespace (myName.id)",
						"param": "fullyQualifiedName"
					},
					{
						"tag": "param",
						"text": "the private key to sign the transaction",
						"param": "publicKey"
					},
					{
						"tag": "param",
						"text": "the Stacks blockchain network to use\n",
						"param": "network"
					}
				]
			},
			"children": [
				{
					"id": 134,
					"name": "fullyQualifiedName",
					"kind": 1024,
					"kindString": "Property",
					"flags": {},
					"sources": [
						{
							"fileName": "index.ts",
							"line": 702,
							"character": 20
						}
					],
					"type": {
						"type": "intrinsic",
						"name": "string"
					}
				},
				{
					"id": 136,
					"name": "network",
					"kind": 1024,
					"kindString": "Property",
					"flags": {},
					"sources": [
						{
							"fileName": "index.ts",
							"line": 704,
							"character": 9
						}
					],
					"type": {
						"type": "reference",
						"name": "StacksNetwork"
					}
				},
				{
					"id": 135,
					"name": "publicKey",
					"kind": 1024,
					"kindString": "Property",
					"flags": {},
					"sources": [
						{
							"fileName": "index.ts",
							"line": 703,
							"character": 11
						}
					],
					"type": {
						"type": "intrinsic",
						"name": "string"
					}
				}
			],
			"groups": [
				{
					"title": "Properties",
					"kind": 1024,
					"children": [
						134,
						136,
						135
					]
				}
			],
			"sources": [
				{
					"fileName": "index.ts",
					"line": 701,
					"character": 34
				}
			]
		},
		{
			"id": 127,
			"name": "TransferNameOptions",
			"kind": 256,
			"kindString": "Interface",
			"flags": {},
			"comment": {
				"shortText": "Transfer name options",
				"tags": [
					{
						"tag": "param",
						"text": "the fully qualified name to transfer including the\n                                       namespace (myName.id)",
						"param": "fullyQualifiedName"
					},
					{
						"tag": "param",
						"text": "the recipient address of the name transfer",
						"param": "newOwnerAddress"
					},
					{
						"tag": "param",
						"text": "the optional zonefile to register with the name",
						"param": "zonefile"
					},
					{
						"tag": "param",
						"text": "the private key to sign the transaction",
						"param": "publicKey"
					},
					{
						"tag": "param",
						"text": "the Stacks blockchain network to use\n",
						"param": "network"
					}
				]
			},
			"children": [
				{
					"id": 128,
					"name": "fullyQualifiedName",
					"kind": 1024,
					"kindString": "Property",
					"flags": {},
					"sources": [
						{
							"fileName": "index.ts",
							"line": 640,
							"character": 20
						}
					],
					"type": {
						"type": "intrinsic",
						"name": "string"
					}
				},
				{
					"id": 131,
					"name": "network",
					"kind": 1024,
					"kindString": "Property",
					"flags": {},
					"sources": [
						{
							"fileName": "index.ts",
							"line": 643,
							"character": 9
						}
					],
					"type": {
						"type": "reference",
						"name": "StacksNetwork"
					}
				},
				{
					"id": 129,
					"name": "newOwnerAddress",
					"kind": 1024,
					"kindString": "Property",
					"flags": {},
					"sources": [
						{
							"fileName": "index.ts",
							"line": 641,
							"character": 17
						}
					],
					"type": {
						"type": "intrinsic",
						"name": "string"
					}
				},
				{
					"id": 130,
					"name": "publicKey",
					"kind": 1024,
					"kindString": "Property",
					"flags": {},
					"sources": [
						{
							"fileName": "index.ts",
							"line": 642,
							"character": 11
						}
					],
					"type": {
						"type": "intrinsic",
						"name": "string"
					}
				},
				{
					"id": 132,
					"name": "zonefile",
					"kind": 1024,
					"kindString": "Property",
					"flags": {
						"isOptional": true
					},
					"sources": [
						{
							"fileName": "index.ts",
							"line": 644,
							"character": 10
						}
					],
					"type": {
						"type": "intrinsic",
						"name": "string"
					}
				}
			],
			"groups": [
				{
					"title": "Properties",
					"kind": 1024,
					"children": [
						128,
						131,
						129,
						130,
						132
					]
				}
			],
			"sources": [
				{
					"fileName": "index.ts",
					"line": 639,
					"character": 36
				}
			]
		},
		{
			"id": 122,
			"name": "UpdateNameOptions",
			"kind": 256,
			"kindString": "Interface",
			"flags": {},
			"comment": {
				"shortText": "Update name options",
				"tags": [
					{
						"tag": "param",
						"text": "the fully qualified name to update including the\n                                       namespace (myName.id)",
						"param": "fullyQualifiedName"
					},
					{
						"tag": "param",
						"text": "the zonefile to register with the name",
						"param": "zonefile"
					},
					{
						"tag": "param",
						"text": "the private key to sign the transaction",
						"param": "publicKey"
					},
					{
						"tag": "param",
						"text": "the Stacks blockchain network to use\n",
						"param": "network"
					}
				]
			},
			"children": [
				{
					"id": 123,
					"name": "fullyQualifiedName",
					"kind": 1024,
					"kindString": "Property",
					"flags": {},
					"sources": [
						{
							"fileName": "index.ts",
							"line": 591,
							"character": 20
						}
					],
					"type": {
						"type": "intrinsic",
						"name": "string"
					}
				},
				{
					"id": 126,
					"name": "network",
					"kind": 1024,
					"kindString": "Property",
					"flags": {},
					"sources": [
						{
							"fileName": "index.ts",
							"line": 594,
							"character": 9
						}
					],
					"type": {
						"type": "reference",
						"name": "StacksNetwork"
					}
				},
				{
					"id": 125,
					"name": "publicKey",
					"kind": 1024,
					"kindString": "Property",
					"flags": {},
					"sources": [
						{
							"fileName": "index.ts",
							"line": 593,
							"character": 11
						}
					],
					"type": {
						"type": "intrinsic",
						"name": "string"
					}
				},
				{
					"id": 124,
					"name": "zonefile",
					"kind": 1024,
					"kindString": "Property",
					"flags": {},
					"sources": [
						{
							"fileName": "index.ts",
							"line": 592,
							"character": 10
						}
					],
					"type": {
						"type": "intrinsic",
						"name": "string"
					}
				}
			],
			"groups": [
				{
					"title": "Properties",
					"kind": 1024,
					"children": [
						123,
						126,
						125,
						124
					]
				}
			],
			"sources": [
				{
					"fileName": "index.ts",
					"line": 590,
					"character": 34
				}
			]
		},
		{
			"id": 40,
			"name": "BNS_CONTRACT_NAME",
			"kind": 32,
			"kindString": "Variable",
			"flags": {
				"isConst": true
			},
			"sources": [
				{
					"fileName": "index.ts",
					"line": 27,
					"character": 30
				}
			],
			"type": {
				"type": "literal",
				"value": "bns"
			},
			"defaultValue": "'bns'"
		},
		{
			"id": 16,
			"name": "buildImportNameTx",
			"kind": 64,
			"kindString": "Function",
			"flags": {},
			"sources": [
				{
					"fileName": "index.ts",
					"line": 408,
					"character": 39
				}
			],
			"signatures": [
				{
					"id": 17,
					"name": "buildImportNameTx",
					"kind": 4096,
					"kindString": "Call signature",
					"flags": {},
					"comment": {
						"shortText": "Generates a namespace name import transaction.\nAn optional step in namespace registration.",
						"text": "Resolves to the generated StacksTransaction\n",
						"returns": "\n"
					},
					"parameters": [
						{
							"id": 18,
							"name": "__namedParameters",
							"kind": 32768,
							"kindString": "Parameter",
							"flags": {},
							"type": {
								"type": "reference",
								"id": 99,
								"name": "ImportNameOptions"
							}
						}
					],
					"type": {
						"type": "reference",
						"typeArguments": [
							{
								"type": "reference",
								"name": "StacksTransaction"
							}
						],
						"name": "Promise"
					}
				}
			]
		},
		{
			"id": 22,
			"name": "buildPreorderNameTx",
			"kind": 64,
			"kindString": "Function",
			"flags": {},
			"sources": [
				{
					"fileName": "index.ts",
					"line": 501,
					"character": 41
				}
			],
			"signatures": [
				{
					"id": 23,
					"name": "buildPreorderNameTx",
					"kind": 4096,
					"kindString": "Call signature",
					"flags": {},
					"comment": {
						"shortText": "Generates a name preorder transaction.\nFirst step in registering a name. This transaction does not reveal the name that is\nabout to be registered. And it sets the amount of STX to be burned for the registration.",
						"text": "Resolves to the generated StacksTransaction\n",
						"returns": "\n"
					},
					"parameters": [
						{
							"id": 24,
							"name": "__namedParameters",
							"kind": 32768,
							"kindString": "Parameter",
							"flags": {},
							"type": {
								"type": "reference",
								"id": 110,
								"name": "PreorderNameOptions"
							}
						}
					],
					"type": {
						"type": "reference",
						"typeArguments": [
							{
								"type": "reference",
								"name": "StacksTransaction"
							}
						],
						"name": "Promise"
					}
				}
			]
		},
		{
			"id": 10,
			"name": "buildPreorderNamespaceTx",
			"kind": 64,
			"kindString": "Function",
			"flags": {},
			"sources": [
				{
					"fileName": "index.ts",
					"line": 285,
					"character": 46
				}
			],
			"signatures": [
				{
					"id": 11,
					"name": "buildPreorderNamespaceTx",
					"kind": 4096,
					"kindString": "Call signature",
					"flags": {},
					"comment": {
						"shortText": "Generates a namespace preorder transaction.\nFirst step in registering a namespace. This transaction does not reveal the namespace that is\nabout to be registered. And it sets the amount of STX to be burned for the registration.",
						"text": "Resolves to the generated StacksTransaction\n",
						"returns": "\n"
					},
					"parameters": [
						{
							"id": 12,
							"name": "__namedParameters",
							"kind": 32768,
							"kindString": "Parameter",
							"flags": {},
							"type": {
								"type": "reference",
								"id": 85,
								"name": "PreorderNamespaceOptions"
							}
						}
					],
					"type": {
						"type": "reference",
						"typeArguments": [
							{
								"type": "reference",
								"name": "StacksTransaction"
							}
						],
						"name": "Promise"
					}
				}
			]
		},
		{
			"id": 19,
			"name": "buildReadyNamespaceTx",
			"kind": 64,
			"kindString": "Function",
			"flags": {},
			"sources": [
				{
					"fileName": "index.ts",
					"line": 457,
					"character": 43
				}
			],
			"signatures": [
				{
					"id": 20,
					"name": "buildReadyNamespaceTx",
					"kind": 4096,
					"kindString": "Call signature",
					"flags": {},
					"comment": {
						"shortText": "Generates a ready namespace transaction.\nFinal step in namespace registration. This completes the namespace registration and\nmakes the namespace available for name registrations.",
						"text": "Resolves to the generated StacksTransaction\n",
						"returns": "\n"
					},
					"parameters": [
						{
							"id": 21,
							"name": "__namedParameters",
							"kind": 32768,
							"kindString": "Parameter",
							"flags": {},
							"type": {
								"type": "reference",
								"id": 106,
								"name": "ReadyNamespaceOptions"
							}
						}
					],
					"type": {
						"type": "reference",
						"typeArguments": [
							{
								"type": "reference",
								"name": "StacksTransaction"
							}
						],
						"name": "Promise"
					}
				}
			]
		},
		{
			"id": 25,
			"name": "buildRegisterNameTx",
			"kind": 64,
			"kindString": "Function",
			"flags": {},
			"sources": [
				{
					"fileName": "index.ts",
					"line": 552,
					"character": 41
				}
			],
			"signatures": [
				{
					"id": 26,
					"name": "buildRegisterNameTx",
					"kind": 4096,
					"kindString": "Call signature",
					"flags": {},
					"comment": {
						"shortText": "Generates a name registration transaction.\nSecond and final step in registering a name.",
						"text": "Resolves to the generated StacksTransaction\n",
						"returns": "\n"
					},
					"parameters": [
						{
							"id": 27,
							"name": "__namedParameters",
							"kind": 32768,
							"kindString": "Parameter",
							"flags": {},
							"type": {
								"type": "reference",
								"id": 116,
								"name": "RegisterNameOptions"
							}
						}
					],
					"type": {
						"type": "reference",
						"typeArguments": [
							{
								"type": "reference",
								"name": "StacksTransaction"
							}
						],
						"name": "Promise"
					}
				}
			]
		},
		{
			"id": 37,
			"name": "buildRenewNameTx",
			"kind": 64,
			"kindString": "Function",
			"flags": {},
			"sources": [
				{
					"fileName": "index.ts",
					"line": 766,
					"character": 38
				}
			],
			"signatures": [
				{
					"id": 38,
					"name": "buildRenewNameTx",
					"kind": 4096,
					"kindString": "Call signature",
					"flags": {},
					"comment": {
						"shortText": "Generates a name renew transaction.\nThis renews a name registration.",
						"text": "Resolves to the generated StacksTransaction\n",
						"returns": "\n"
					},
					"parameters": [
						{
							"id": 39,
							"name": "__namedParameters",
							"kind": 32768,
							"kindString": "Parameter",
							"flags": {},
							"type": {
								"type": "reference",
								"id": 137,
								"name": "RenewNameOptions"
							}
						}
					],
					"type": {
						"type": "reference",
						"typeArguments": [
							{
								"type": "reference",
								"name": "StacksTransaction"
							}
						],
						"name": "Promise"
					}
				}
			]
		},
		{
			"id": 13,
			"name": "buildRevealNamespaceTx",
			"kind": 64,
			"kindString": "Function",
			"flags": {},
			"sources": [
				{
					"fileName": "index.ts",
					"line": 335,
					"character": 44
				}
			],
			"signatures": [
				{
					"id": 14,
					"name": "buildRevealNamespaceTx",
					"kind": 4096,
					"kindString": "Call signature",
					"flags": {},
					"comment": {
						"shortText": "Generates a namespace reveal transaction.\nSecond step in registering a namespace.",
						"text": "Resolves to the generated StacksTransaction\n",
						"returns": "\n"
					},
					"parameters": [
						{
							"id": 15,
							"name": "__namedParameters",
							"kind": 32768,
							"kindString": "Parameter",
							"flags": {},
							"type": {
								"type": "reference",
								"id": 91,
								"name": "RevealNamespaceOptions"
							}
						}
					],
					"type": {
						"type": "reference",
						"typeArguments": [
							{
								"type": "reference",
								"name": "StacksTransaction"
							}
						],
						"name": "Promise"
					}
				}
			]
		},
		{
			"id": 34,
			"name": "buildRevokeNameTx",
			"kind": 64,
			"kindString": "Function",
			"flags": {},
			"sources": [
				{
					"fileName": "index.ts",
					"line": 717,
					"character": 39
				}
			],
			"signatures": [
				{
					"id": 35,
					"name": "buildRevokeNameTx",
					"kind": 4096,
					"kindString": "Call signature",
					"flags": {},
					"comment": {
						"shortText": "Generates a name revoke transaction.\nThis revokes a name registration.",
						"text": "Resolves to the generated StacksTransaction\n",
						"returns": "\n"
					},
					"parameters": [
						{
							"id": 36,
							"name": "__namedParameters",
							"kind": 32768,
							"kindString": "Parameter",
							"flags": {},
							"type": {
								"type": "reference",
								"id": 133,
								"name": "RevokeNameOptions"
							}
						}
					],
					"type": {
						"type": "reference",
						"typeArguments": [
							{
								"type": "reference",
								"name": "StacksTransaction"
							}
						],
						"name": "Promise"
					}
				}
			]
		},
		{
			"id": 31,
			"name": "buildTransferNameTx",
			"kind": 64,
			"kindString": "Function",
			"flags": {},
			"sources": [
				{
					"fileName": "index.ts",
					"line": 661,
					"character": 41
				}
			],
			"signatures": [
				{
					"id": 32,
					"name": "buildTransferNameTx",
					"kind": 4096,
					"kindString": "Call signature",
					"flags": {},
					"comment": {
						"shortText": "Generates a name transfer transaction.\nThis changes the owner of the registered name.",
						"text": "Since the underlying NFT will be transferred,\nyou will be required to add a post-condition to this\ntransaction before broadcasting it.\n\nResolves to the generated StacksTransaction\n",
						"returns": "\n"
					},
					"parameters": [
						{
							"id": 33,
							"name": "__namedParameters",
							"kind": 32768,
							"kindString": "Parameter",
							"flags": {},
							"type": {
								"type": "reference",
								"id": 127,
								"name": "TransferNameOptions"
							}
						}
					],
					"type": {
						"type": "reference",
						"typeArguments": [
							{
								"type": "reference",
								"name": "StacksTransaction"
							}
						],
						"name": "Promise"
					}
				}
			]
		},
		{
			"id": 28,
			"name": "buildUpdateNameTx",
			"kind": 64,
			"kindString": "Function",
			"flags": {},
			"sources": [
				{
					"fileName": "index.ts",
					"line": 607,
					"character": 39
				}
			],
			"signatures": [
				{
					"id": 29,
					"name": "buildUpdateNameTx",
					"kind": 4096,
					"kindString": "Call signature",
					"flags": {},
					"comment": {
						"shortText": "Generates a name update transaction.\nThis changes the zonefile for the registered name.",
						"text": "Resolves to the generated StacksTransaction\n",
						"returns": "\n"
					},
					"parameters": [
						{
							"id": 30,
							"name": "__namedParameters",
							"kind": 32768,
							"kindString": "Parameter",
							"flags": {},
							"type": {
								"type": "reference",
								"id": 122,
								"name": "UpdateNameOptions"
							}
						}
					],
					"type": {
						"type": "reference",
						"typeArguments": [
							{
								"type": "reference",
								"name": "StacksTransaction"
							}
						],
						"name": "Promise"
					}
				}
			]
		},
		{
			"id": 1,
			"name": "canRegisterName",
			"kind": 64,
			"kindString": "Function",
			"flags": {},
			"sources": [
				{
					"fileName": "index.ts",
					"line": 122,
					"character": 37
				}
			],
			"signatures": [
				{
					"id": 2,
					"name": "canRegisterName",
					"kind": 4096,
					"kindString": "Call signature",
					"flags": {},
					"comment": {
						"shortText": "Check if name can be registered",
						"returns": "that resolves to true if the operation succeeds\n"
					},
					"parameters": [
						{
							"id": 3,
							"name": "__namedParameters",
							"kind": 32768,
							"kindString": "Parameter",
							"flags": {},
							"type": {
								"type": "reference",
								"id": 76,
								"name": "CanRegisterNameOptions"
							}
						}
					],
					"type": {
						"type": "reference",
						"typeArguments": [
							{
								"type": "intrinsic",
								"name": "boolean"
							}
						],
						"name": "Promise"
					}
				}
			]
		},
		{
			"id": 7,
			"name": "getNamePrice",
			"kind": 64,
			"kindString": "Function",
			"flags": {},
			"sources": [
				{
					"fileName": "index.ts",
					"line": 222,
					"character": 34
				}
			],
			"signatures": [
				{
					"id": 8,
					"name": "getNamePrice",
					"kind": 4096,
					"kindString": "Call signature",
					"flags": {},
					"comment": {
						"shortText": "Get price of name registration in microstacks",
						"returns": "that resolves to a BN object number of microstacks if the operation succeeds\n"
					},
					"parameters": [
						{
							"id": 9,
							"name": "__namedParameters",
							"kind": 32768,
							"kindString": "Parameter",
							"flags": {},
							"type": {
								"type": "reference",
								"id": 82,
								"name": "GetNamePriceOptions"
							}
						}
					],
					"type": {
						"type": "reference",
						"typeArguments": [
							{
								"type": "reference",
								"name": "BN"
							}
						],
						"name": "Promise"
					}
				}
			]
		},
		{
			"id": 4,
			"name": "getNamespacePrice",
			"kind": 64,
			"kindString": "Function",
			"flags": {},
			"sources": [
				{
					"fileName": "index.ts",
					"line": 171,
					"character": 39
				}
			],
			"signatures": [
				{
					"id": 5,
					"name": "getNamespacePrice",
					"kind": 4096,
					"kindString": "Call signature",
					"flags": {},
					"comment": {
						"shortText": "Get price of namespace registration in microstacks",
						"returns": "that resolves to a BN object number of microstacks if the operation succeeds\n"
					},
					"parameters": [
						{
							"id": 6,
							"name": "__namedParameters",
							"kind": 32768,
							"kindString": "Parameter",
							"flags": {},
							"type": {
								"type": "reference",
								"id": 79,
								"name": "GetNamespacePriceOptions"
							}
						}
					],
					"type": {
						"type": "reference",
						"typeArguments": [
							{
								"type": "reference",
								"name": "BN"
							}
						],
						"name": "Promise"
					}
				}
			]
		}
	],
	"groups": [
		{
			"title": "Enumerations",
			"kind": 4,
			"children": [
				41
			]
		},
		{
			"title": "Interfaces",
			"kind": 256,
			"children": [
				65,
				71,
				76,
				82,
				79,
				99,
				110,
				85,
				44,
				106,
				116,
				137,
				91,
				133,
				127,
				122
			]
		},
		{
			"title": "Variables",
			"kind": 32,
			"children": [
				40
			]
		},
		{
			"title": "Functions",
			"kind": 64,
			"children": [
				16,
				22,
				10,
				19,
				25,
				37,
				13,
				34,
				31,
				28,
				1,
				7,
				4
			]
		}
	],
	"sources": [
		{
			"fileName": "index.ts",
			"line": 1,
			"character": 0
		}
	]
}